emojirades/__init__.py
emojirades/bot.py
emojirades/checks.py
emojirades/gamestate.py
emojirades/helpers.py
emojirades/scorekeeper.py
emojirades/wrappers.py
emojirades/analytics/__init__.py
emojirades/analytics/scoreboard.py
emojirades/analytics/time_range.py
emojirades/analytics/time_unit.py
emojirades/commands/__init__.py
emojirades/commands/registry.py
emojirades/commands/gamestate_commands/__init__.py
emojirades/commands/gamestate_commands/correct_guess_command.py
emojirades/commands/gamestate_commands/fixwinner_command.py
emojirades/commands/gamestate_commands/game_status.py
emojirades/commands/gamestate_commands/inferred_correct_guess_command.py
emojirades/commands/gamestate_commands/newgame_command.py
emojirades/commands/gamestate_commands/remove_admin_command.py
emojirades/commands/gamestate_commands/set_admin_command.py
emojirades/commands/gamestate_commands/set_emojirade_command.py
emojirades/commands/general_commands/__init__.py
emojirades/commands/general_commands/help_command.py
emojirades/commands/scorekeeper_commands/__init__.py
emojirades/commands/scorekeeper_commands/history_command.py
emojirades/commands/scorekeeper_commands/minusminus_command.py
emojirades/commands/scorekeeper_commands/scoreboard_command.py
emojirades/commands/scorekeeper_commands/set_command.py
emojirades/persistence/__init__.py
emojirades/persistence/orm.py
emojirades/persistence/handlers/__init__.py
emojirades/persistence/handlers/auth.py
emojirades/persistence/handlers/gamestate.py
emojirades/persistence/handlers/scorekeeper.py
emojirades/persistence/handlers/workspace.py
emojirades/persistence/models/__init__.py
emojirades/persistence/models/alembic.ini
emojirades/persistence/models/base.py
emojirades/persistence/models/gamestate.py
emojirades/persistence/models/scorekeeper.py
emojirades/persistence/models/alembic/__init__.py
emojirades/persistence/models/alembic/env.py
emojirades/persistence/models/alembic/versions/2a7a559e761b_initial_models.py
emojirades-1.12.0.dist-info/licenses/LICENSE
emojirades-1.12.0.dist-info/METADATA
emojirades-1.12.0.dist-info/WHEEL
emojirades-1.12.0.dist-info/top_level.txt
emojirades-1.12.0.dist-info/RECORD
