Metadata-Version: 2.4
Name: emojirades
Version: 1.12.0
Summary: Slack bot that understands the Emojirades game!
Home-page: https://github.com/emojirades/emojirades
Author: The Emojirades Team
Author-email: support@emojirades.io
Keywords: slack slackbot emojirades plusplus game
Classifier: Development Status :: 5 - Production/Stable
Classifier: Operating System :: POSIX :: Linux
Classifier: Programming Language :: Python
Classifier: Programming Language :: Python :: 3
Classifier: Programming Language :: Python :: 3.12
Classifier: Programming Language :: Python :: 3.13
Classifier: Programming Language :: Python :: 3.14
Classifier: Topic :: Communications :: Chat
Classifier: Topic :: Games/Entertainment
Requires-Python: >=3.12
License-File: LICENSE
Requires-Dist: slack_sdk~=3.39.0
Requires-Dist: requests~=2.32.3
Requires-Dist: boto3~=1.42.30
Requires-Dist: Unidecode~=1.4.0
Requires-Dist: expiringdict~=1.2.2
Requires-Dist: SQLAlchemy~=2.0.9
Requires-Dist: alembic~=1.18.1
Requires-Dist: psycopg2-binary~=2.9.5
Requires-Dist: python-json-logger~=4.0.0
Provides-Extra: dev
Requires-Dist: pytest~=9.0.2; extra == "dev"
Requires-Dist: pylint~=4.0.3; extra == "dev"
Requires-Dist: black~=25.12.0; extra == "dev"
Requires-Dist: websockets~=16.0; extra == "dev"
Dynamic: license-file
